<?xml version="1.0" encoding="UTF-8"?>
<!DOCTYPE mapper PUBLIC "-//mybatis.org//DTD Mapper 3.0//EN" "http://mybatis.org/dtd/mybatis-3-mapper.dtd">
<mapper namespace="cj.springboot.wiki.security.rbac.dao.CjAuthRoleDao">

    <!-- 通用查询映射结果 -->
    <resultMap id="BaseResultMap" type="cj.springboot.wiki.security.rbac.entity.CjAuthRoleEntity">
        <id column="id" property="id" />
        <result column="cjuniversal_create_time" property="cjuniversalCreateTime" />
        <result column="cjuniversal_del_status" property="cjuniversalDelStatus" />
        <result column="cjuniversal_update_time" property="cjuniversalUpdateTime" />
        <result column="name" property="name" />
        <result column="roleDesc" property="roleDesc" />
        <result column="roleTag" property="roleTag" />
    </resultMap>

</mapper>
